wabisabi/__init__.py
wabisabi/_static_version.py
wabisabi/_version.py
wabisabi/default_parameter_change.py
wabisabi/docscrape.py
wabisabi/kwarg_name_change.py
wabisabi/kwonly_change.py
wabisabi/merge_docstrings.py
wabisabi/tests/__init__.py
wabisabi/tests/test_default_parameter_change.py
wabisabi/tests/test_default_parameter_change_numpydoc.py
wabisabi/tests/test_kwarg_name_change_deprecation.py
wabisabi/tests/test_kwonly_deprecation.py
wabisabi-0.3.0.dist-info/LICENSE
wabisabi-0.3.0.dist-info/METADATA
wabisabi-0.3.0.dist-info/WHEEL
wabisabi-0.3.0.dist-info/top_level.txt
wabisabi-0.3.0.dist-info/RECORD
