Metadata-Version: 2.1
Name: wabisabi
Version: 0.3.0
Summary: Deprecate your code effortlessly with decorators. Give useful warnings and docstrings for different deprecations.
Home-page: https://github.com/hmaarrfk/wabisabi
Author: Mark Harfouche
Author-email: mark.harfouche@gmail.com
License: BSD license
Keywords: deprecation factory wabisabi
Classifier: Development Status :: 2 - Pre-Alpha
Classifier: Intended Audience :: Developers
Classifier: License :: OSI Approved :: BSD License
Classifier: Natural Language :: English
Classifier: Programming Language :: Python :: 3
Classifier: Programming Language :: Python :: 3.8
Classifier: Programming Language :: Python :: 3.9
Classifier: Programming Language :: Python :: 3.10
Classifier: Programming Language :: Python :: 3.11
Requires-Python: >=3.8
License-File: LICENSE
Requires-Dist: packaging
